pyswarms/__init__.py
pyswarms/backend/__init__.py
pyswarms/backend/generators.py
pyswarms/backend/handlers.py
pyswarms/backend/operators.py
pyswarms/backend/swarms.py
pyswarms/backend/topology/__init__.py
pyswarms/backend/topology/base.py
pyswarms/backend/topology/pyramid.py
pyswarms/backend/topology/random.py
pyswarms/backend/topology/ring.py
pyswarms/backend/topology/star.py
pyswarms/backend/topology/von_neumann.py
pyswarms/base/__init__.py
pyswarms/base/base_discrete.py
pyswarms/base/base_single.py
pyswarms/discrete/__init__.py
pyswarms/discrete/binary.py
pyswarms/single/__init__.py
pyswarms/single/general_optimizer.py
pyswarms/single/global_best.py
pyswarms/single/local_best.py
pyswarms/utils/__init__.py
pyswarms/utils/decorators/__init__.py
pyswarms/utils/decorators/decorators.py
pyswarms/utils/functions/__init__.py
pyswarms/utils/functions/single_obj.py
pyswarms/utils/plotters/__init__.py
pyswarms/utils/plotters/formatters.py
pyswarms/utils/plotters/plotters.py
pyswarms/utils/reporter/__init__.py
pyswarms/utils/reporter/reporter.py
pyswarms/utils/search/__init__.py
pyswarms/utils/search/base_search.py
pyswarms/utils/search/grid_search.py
pyswarms/utils/search/random_search.py
pyswarms-1.3.0.dist-info/METADATA
pyswarms-1.3.0.dist-info/RECORD
pyswarms-1.3.0.dist-info/WHEEL
pyswarms-1.3.0.dist-info/top_level.txt
tests/backend/__init__.py
tests/backend/conftest.py
tests/backend/test_generators.py
tests/backend/test_handlers.py
tests/backend/test_operators.py
tests/backend/topology/__init__.py
tests/backend/topology/abc_test_topology.py
tests/backend/topology/conftest.py
tests/backend/topology/test_pyramid.py
tests/backend/topology/test_random.py
tests/backend/topology/test_ring.py
tests/backend/topology/test_star.py
tests/backend/topology/test_von_neumann.py
tests/optimizers/__init__.py
tests/optimizers/abc_test_discrete_optimizer.py
tests/optimizers/abc_test_optimizer.py
tests/optimizers/test_binary.py
tests/optimizers/test_general_optimizer.py
tests/optimizers/test_global_best.py
tests/optimizers/test_local_best.py
