Metadata-Version: 2.1
Name: pyswarms
Version: 1.3.0
Summary: A Python-based Particle Swarm Optimization (PSO) library.
Home-page: https://github.com/ljvmiranda921/pyswarms
Author: Lester James V. Miranda
Author-email: ljvmiranda@gmail.com
License: MIT license
Keywords: pyswarms
Platform: UNKNOWN
Classifier: Development Status :: 5 - Production/Stable
Classifier: Intended Audience :: Developers
Classifier: Intended Audience :: Education
Classifier: Intended Audience :: Science/Research
Classifier: License :: OSI Approved :: MIT License
Classifier: Natural Language :: English
Classifier: Topic :: Scientific/Engineering
Classifier: Topic :: Scientific/Engineering :: Mathematics
Classifier: Programming Language :: Python :: 3.6
Classifier: Programming Language :: Python :: 3.7
Provides-Extra: test
